<annotation>
	<folder>dosa</folder>
	<filename>178_dosa.jpg</filename>
	<path>/home/ubuntu/Desktop/dataset/dosa/178_dosa.jpg</path>
	<source>
		<database>Unknown</database>
	</source>
	<size>
		<width>128</width>
		<height>128</height>
		<depth>3</depth>
	</size>
	<segmented>0</segmented>
	<object>
		<name>dosa</name>
		<pose>Unspecified</pose>
		<truncated>1</truncated>
		<difficult>0</difficult>
		<bndbox>
			<xmin>2</xmin>
			<ymin>32</ymin>
			<xmax>128</xmax>
			<ymax>123</ymax>
		</bndbox>
	</object>
</annotation>
