<annotation>
	<folder>idly</folder>
	<filename>120_Idly.jpg</filename>
	<path>/home/ubuntu/Desktop/dataset/idly/120_Idly.jpg</path>
	<source>
		<database>Unknown</database>
	</source>
	<size>
		<width>128</width>
		<height>128</height>
		<depth>3</depth>
	</size>
	<segmented>0</segmented>
	<object>
		<name>idly</name>
		<pose>Unspecified</pose>
		<truncated>0</truncated>
		<difficult>0</difficult>
		<bndbox>
			<xmin>58</xmin>
			<ymin>36</ymin>
			<xmax>83</xmax>
			<ymax>55</ymax>
		</bndbox>
	</object>
	<object>
		<name>idly</name>
		<pose>Unspecified</pose>
		<truncated>0</truncated>
		<difficult>0</difficult>
		<bndbox>
			<xmin>37</xmin>
			<ymin>39</ymin>
			<xmax>59</xmax>
			<ymax>61</ymax>
		</bndbox>
	</object>
	<object>
		<name>idly</name>
		<pose>Unspecified</pose>
		<truncated>0</truncated>
		<difficult>0</difficult>
		<bndbox>
			<xmin>60</xmin>
			<ymin>62</ymin>
			<xmax>85</xmax>
			<ymax>83</ymax>
		</bndbox>
	</object>
	<object>
		<name>idly</name>
		<pose>Unspecified</pose>
		<truncated>0</truncated>
		<difficult>0</difficult>
		<bndbox>
			<xmin>22</xmin>
			<ymin>50</ymin>
			<xmax>44</xmax>
			<ymax>74</ymax>
		</bndbox>
	</object>
	<object>
		<name>idly</name>
		<pose>Unspecified</pose>
		<truncated>0</truncated>
		<difficult>0</difficult>
		<bndbox>
			<xmin>19</xmin>
			<ymin>82</ymin>
			<xmax>38</xmax>
			<ymax>105</ymax>
		</bndbox>
	</object>
	<object>
		<name>idly</name>
		<pose>Unspecified</pose>
		<truncated>0</truncated>
		<difficult>0</difficult>
		<bndbox>
			<xmin>39</xmin>
			<ymin>95</ymin>
			<xmax>64</xmax>
			<ymax>111</ymax>
		</bndbox>
	</object>
	<object>
		<name>idly</name>
		<pose>Unspecified</pose>
		<truncated>0</truncated>
		<difficult>0</difficult>
		<bndbox>
			<xmin>49</xmin>
			<ymin>108</ymin>
			<xmax>74</xmax>
			<ymax>123</ymax>
		</bndbox>
	</object>
	<object>
		<name>idly</name>
		<pose>Unspecified</pose>
		<truncated>0</truncated>
		<difficult>0</difficult>
		<bndbox>
			<xmin>69</xmin>
			<ymin>81</ymin>
			<xmax>90</xmax>
			<ymax>96</ymax>
		</bndbox>
	</object>
	<object>
		<name>idly</name>
		<pose>Unspecified</pose>
		<truncated>0</truncated>
		<difficult>0</difficult>
		<bndbox>
			<xmin>38</xmin>
			<ymin>76</ymin>
			<xmax>63</xmax>
			<ymax>96</ymax>
		</bndbox>
	</object>
	<object>
		<name>idly</name>
		<pose>Unspecified</pose>
		<truncated>0</truncated>
		<difficult>0</difficult>
		<bndbox>
			<xmin>69</xmin>
			<ymin>95</ymin>
			<xmax>94</xmax>
			<ymax>108</ymax>
		</bndbox>
	</object>
	<object>
		<name>idly</name>
		<pose>Unspecified</pose>
		<truncated>0</truncated>
		<difficult>0</difficult>
		<bndbox>
			<xmin>73</xmin>
			<ymin>106</ymin>
			<xmax>94</xmax>
			<ymax>123</ymax>
		</bndbox>
	</object>
</annotation>
