<annotation>
	<folder>cutlet</folder>
	<filename>45_cutlet.jpg</filename>
	<path>/home/ubuntu/Desktop/dataset/cutlet/45_cutlet.jpg</path>
	<source>
		<database>Unknown</database>
	</source>
	<size>
		<width>128</width>
		<height>128</height>
		<depth>3</depth>
	</size>
	<segmented>0</segmented>
	<object>
		<name>cutlet</name>
		<pose>Unspecified</pose>
		<truncated>0</truncated>
		<difficult>0</difficult>
		<bndbox>
			<xmin>41</xmin>
			<ymin>50</ymin>
			<xmax>85</xmax>
			<ymax>108</ymax>
		</bndbox>
	</object>
	<object>
		<name>cutlet</name>
		<pose>Unspecified</pose>
		<truncated>0</truncated>
		<difficult>0</difficult>
		<bndbox>
			<xmin>82</xmin>
			<ymin>55</ymin>
			<xmax>127</xmax>
			<ymax>100</ymax>
		</bndbox>
	</object>
	<object>
		<name>cutlet</name>
		<pose>Unspecified</pose>
		<truncated>0</truncated>
		<difficult>0</difficult>
		<bndbox>
			<xmin>45</xmin>
			<ymin>27</ymin>
			<xmax>92</xmax>
			<ymax>57</ymax>
		</bndbox>
	</object>
</annotation>
